skomerchecker/__init__.py
skomerchecker/const.py
skomerchecker/skomerchecker.py
skomerchecker-0.0.1.dist-info/LICENSE.md
skomerchecker-0.0.1.dist-info/METADATA
skomerchecker-0.0.1.dist-info/WHEEL
skomerchecker-0.0.1.dist-info/top_level.txt
skomerchecker-0.0.1.dist-info/RECORD
