Metadata-Version: 2.1
Name: skomerchecker
Version: 0.0.1
Summary: A package to gather information on sailings to Skomer island
Home-page: https://github.com/tombrien/skomerchecker
Author: Tom Brien
Author-email: tom@tombrien.io
Project-URL: Bug Tracker, https://github.com/tombrien/skomerchecker/issues
Classifier: Programming Language :: Python :: 3
Classifier: License :: OSI Approved :: MIT License
Classifier: Operating System :: OS Independent
Requires-Python: >=3.7
License-File: LICENSE.md
Requires-Dist: bs4
Requires-Dist: getuseragent
Requires-Dist: httpx
Requires-Dist: lxml
